palchemy/__init__.py
palchemy/cli.py
palchemy/core/__init__.py
palchemy/core/config.py
palchemy/core/exceptions.py
palchemy/core/palchemy.py
palchemy/llm/__init__.py
palchemy/llm/base.py
palchemy/llm/providers.py
palchemy/utils/__init__.py
palchemy/utils/query_validator.py
palchemy/utils/schema.py
palchemy/utils/security.py
palchemy-0.1.0.dist-info/LICENSE
palchemy-0.1.0.dist-info/METADATA
palchemy-0.1.0.dist-info/WHEEL
palchemy-0.1.0.dist-info/entry_points.txt
palchemy-0.1.0.dist-info/top_level.txt
palchemy-0.1.0.dist-info/RECORD
